[
  {
    "Response": "That's terrible"
  },
  {
    "Response": "Weird"
  },
  {
    "Response": "That sucks"
  },
  {
    "Response": "I don't know"
  },
  {
    "Response": "My bad"
  },
  {
    "Response": "Nothing exciting"
  },
  {
    "Response": "But not yet"
  },
  {
    "Response": "I'm not too sure"
  },
  {
    "Response": "I am confused"
  },
  {
    "Response": "No you don't"
  },
  {
    "Response": "Don't know"
  },
  {
    "Response": "/: Exactly"
  },
  {
    "Response": "Ugh"
  },
  {
    "Response": "Nothing"
  },
  {
    "Response": "I don't get it"
  },
  {
    "Response": "I don't think so"
  },
  {
    "Response": "Yeah sorry"
  },
  {
    "Response": "Sigh"
  },
  {
    "Response": "I was confused"
  },
  {
    "Response": "/:"
  },
  {
    "Response": "I don't understand your question"
  },
  {
    "Response": "It's terrible"
  },
  {
    "Response": "No!"
  },
  {
    "Response": "Sorry!"
  },
  {
    "Response": "Not sure though"
  },
  {
    "Response": "Very sorry"
  },
  {
    "Response": "What were you thinking?"
  },
  {
    "Response": "I don't know"
  },
  {
    "Response": "Sorry I was confused"
  },
  {
    "Response": "I don't understand"
  },
  {
    "Response": "Ouch"
  },
  {
    "Response": "No you didn't"
  },
  {
    "Response": "That is wrong"
  },
  {
    "Response": ":/"
  },
  {
    "Response": "no"
  },
  {
    "Response": "Nope. Why?"
  },
  {
    "Response": "Oops Shoot"
  },
  {
    "Response": "Sigh"
  },
  {
    "Response": "No it's not"
  },
  {
    "Response": "Nope!"
  },
  {
    "Response": "No."
  },
  {
    "Response": "Nope"
  },
  {
    "Response": "No, I'm not"
  },
  {
    "Response": "No you're not"
  },
  {
    "Response": "Sorry to hear that"
  },
  {
    "Response": "Not really"
  }
]